<ListaDeProductos>
  <DatosProducto>
    <codigo>11</codigo>
    <producto>PC</producto>
    <precio>1022.57</precio>
  </DatosProducto>
  <DatosProducto>
    <codigo>12</codigo>
    <producto>MONITOR</producto>
    <precio>50.15</precio>
  </DatosProducto>
  <DatosProducto>
    <codigo>13</codigo>
    <producto>TECLADO</producto>
    <precio>10.22</precio>
  </DatosProducto>
  <DatosProducto>
    <codigo>14</codigo>
    <producto>RATÓN</producto>
    <precio>2.75</precio>
  </DatosProducto>
  <DatosProducto>
    <codigo>15</codigo>
    <producto>PENDRIVE</producto>
    <precio>30.2</precio>
  </DatosProducto>
  <DatosProducto>
    <codigo>16</codigo>
    <producto>CABLEAVG</producto>
    <precio>5.3</precio>
  </DatosProducto>
  <DatosProducto>
    <codigo>17</codigo>
    <producto>CABLEHDMI</producto>
    <precio>10.22</precio>
  </DatosProducto>
  <DatosProducto>
    <codigo>18</codigo>
    <producto>PROYECTOR</producto>
    <precio>1002.87</precio>
  </DatosProducto>
</ListaDeProductos>